8_bit_ALU/comparator4.v
// Name: Yaohong Sabotinova
// 4-bit comparator

module comparator4(a,b,eq,gt,lt,e,g,l); //sub- module for 4-bit magnitude comparator

input [3:0]a,b;
input eq,gt,lt;
output e,g,l;
wire [3:0]x,bbar;
// ,abar;

wire w1,w2,w3,w4,w5,ebar,gbar;
// w5,w6,w7,w8;

xnor z3(x[3],a[3],b[3]);
xnor z2(x[2],a[2],b[2]);
xnor z1(x[1],a[1],b[1]);
xnor z0(x[0],a[0],b[0]);

not n3(bbar[3],b[3]);
not n2(bbar[2],b[2]);
not n1(bbar[1],b[1]);
not n0(bbar[0],b[0]);

// not na3(abar[3],a[3]);
// not na2(abar[2],a[2]);
// not na1(abar[1],a[1]);
// not na0(abar[0],a[0]);


and q1(w1,a[3],bbar[3]);
and q2(w2,x[3],a[2],bbar[2]);
and q3(w3,x[3],x[2],a[1],bbar[1]);
and q4(w4,x[3],x[2],x[1],a[0],bbar[0]);

// and qa1(w5,b[3],abar[3]);
// and qa2(w6,x[3],b[2],abar[2]);
// and qa3(w7,x[3],x[2],b[1],abar[1]);
// and qa4(w8,x[3],x[2],x[1],b[0],abar[0]);

or o1(g,w1,w2,w3,w4);//greater than
and a1(e,x[0],x[1],x[2],x[3]); //equal
// and o2(l,w5,w6,w7,w8); //less than
not n4(ebar,e);
not n5(gbar,g);
and a2(l,ebar,gbar);

endmodule

8_bit_ALU/comparator8.v
// Name: Yaohong Sabotinova
// 8-bit comparator

module comparator8(eq,lt,gt,a,b);
input [7:0] a, b; 
output eq,gt,lt;
wire e,g,l;

comparator4 c1(a[7:4],b[7:4], {1'b1},{1'b0},{1'b0},eq,gt,lt);
comparator4 c2(a[3:0],b[3:0],eq,gt,lt,e,g,l);

endmodule

8_bit_ALU/comparator8_tb.v

module comparator8_tb;

reg [7:0] a,b;
wire eq,gt,lt;

    initial 
	
		begin

		$dumpfile("comparator8_tb.vcd"); // Simulation results -> GTKWave
        $dumpvars(0,comp01);  // Variables that will be in vcd file

 		$monitor("%b+ %b = %b%b%b", a, b, eq, gt,lt);
		#0  a = 8'b00001000; b =8'b00010000;
		#50 a = 8'b01000010;b = 8'b00010010;
		#50 a = 8'b01000010;b = 8'b01000010;
        #50 a = 8'b01100010;b = 8'b10110010;
        #50 a = 8'b11001011;b = 8'b01010010;
		#50 a = 8'b01000110;b = 8'b01100010;
        #50 a = 8'b01101110;b = 8'b10010010;
        #50 a = 8'b11001110;b = 8'b00010010;
		#50;
 
    end
comparator8 comp01(eq,gt,lt,a,b);

endmodule

8_bit_ALU/comparator8_tb.vcd
$date
	Fri May 15 20:52:01 2020
$end
$version
	Icarus Verilog
$end
$timescale
	1s
$end
$scope module comparator8_tb $end
$scope module comp01 $end
$var wire 8 ! a [7:0] $end
$var wire 8 " b [7:0] $end
$var wire 1 # lt $end
$var wire 1 $ l $end
$var wire 1 % gt $end
$var wire 1 & g $end
$var wire 1 ' eq $end
$var wire 1 ( e $end
$scope module c1 $end
$var wire 4 ) a [3:0] $end
$var wire 4 * b [3:0] $end
$var wire 1 ' e $end
$var wire 1 + ebar $end
$var wire 1 , eq $end
$var wire 1 % g $end
$var wire 1 - gbar $end
$var wire 1 . gt $end
$var wire 1 # l $end
$var wire 1 / lt $end
$var wire 1 0 w1 $end
$var wire 1 1 w2 $end
$var wire 1 2 w3 $end
$var wire 1 3 w4 $end
$var wire 4 4 x [3:0] $end
$var wire 4 5 bbar [3:0] $end
$upscope $end
$scope module c2 $end
$var wire 4 6 a [3:0] $end
$var wire 4 7 b [3:0] $end
$var wire 1 ( e $end
$var wire 1 8 ebar $end
$var wire 1 ' eq $end
$var wire 1 & g $end
$var wire 1 9 gbar $end
$var wire 1 % gt $end
$var wire 1 $ l $end
$var wire 1 # lt $end
$var wire 1 : w1 $end
$var wire 1 ; w2 $end
$var wire 1 < w3 $end
$var wire 1 = w4 $end
$var wire 4 > x [3:0] $end
$var wire 4 ? bbar [3:0] $end
$upscope $end
$upscope $end
$upscope $end
$enddefinitions $end
#0
$dumpvars
b1111 ?
b111 >
0=
0<
0;
1:
09
18
b0 7
b1000 6
b1110 5
b1110 4
03
02
01
00
0/
0.
1-
1,
1+
b1 *
b0 )
0(
0'
1&
0%
0$
1#
b10000 "
b1000 !
$end
#50
0#
08
0$
0-
1(
19
1%
0&
b1101 ?
b1010 4
11
b1111 >
0:
b10 7
b100 )
b10 6
b10010 "
b1000010 !
#100
1-
0+
0%
1'
01
b1111 4
b1011 5
b100 *
b1000010 "
#150
1#
1+
0'
1-
0%
b10 4
b100 5
02
b1011 *
b110 )
b10110010 "
b1100010 !
#200
0#
0-
1%
18
10
0(
09
1&
0=
b110 4
b1010 5
b110 >
1:
b101 *
b1100 )
b1011 6
b1010010 "
b11001011 !
#250
1#
0$
1-
1;
09
0%
1&
b1001 5
b1101 4
00
b1011 >
0:
b110 *
b100 )
b110 6
b1100010 "
b1000110 !
#300
0;
b0 4
b110 5
b11 >
1:
b1001 *
b110 )
b1110 6
b10010010 "
b1101110 !
#350
0#
0-
1%
10
b1110 5
b10 4
b1 *
b1100 )
b10010 "
b11001110 !
