8_bit_ALU/Incre_Decre.v
// Name: Yaohong Sabotinova 
//increment and decrement

module Incre_Decre(a,b,sel); 
output [7:0] b;
input [7:0] a; 
input sel;

reg [7:0] b;


always @(*)
begin 
  if (sel == 0) // sel =0 for increment
  begin 
    b = a + 1'b1;
  end
  else if(sel== 1)// sel = 1 for decrement 
  begin
    b = a - 1'b1;
  end
end

endmodule

8_bit_ALU/Incre_Decre_tb.v
module Incre_Decre_tb;

reg [7:0] a;
reg sel;

wire [7:0] b;

   initial
   
     begin
		$display("Simulation running..."); // Display info on monitor
        $dumpfile("Incre_Decre_tb.vcd"); // Simulation results -> GTKWave
        $dumpvars(0,id01);  // Variables that will be in vcd file

        $monitor("%b +%b = %b", a,sel, b);
		#0 	a = 8'b00000101;sel=1;
		#50 a = 8'b00000100;sel=0;
		#50 a = 8'b00010100;sel=1;
		#50 a = 8'b10000101;sel=0;
		#50 a = 8'b10000001;sel=1;
		#50 a = 8'b10010101;sel=0;
		#50 a = 8'b10010000;sel=1;
		#50 a = 8'b10010101;sel=0;
        #50 a = 8'b10010001;sel=1;
		#50 a = 8'b10010100;sel=0;
		#50 $finish;
     end


Incre_Decre id01(a,b,sel);

endmodule

8_bit_ALU/Incre_Decre_tb.vcd
$date
	Fri May 15 19:56:48 2020
$end
$version
	Icarus Verilog
$end
$timescale
	1s
$end
$scope module Incre_Decre_tb $end
$scope module id01 $end
$var wire 8 ! a [7:0] $end
$var wire 1 " sel $end
$var reg 8 # b [7:0] $end
$upscope $end
$upscope $end
$enddefinitions $end
#0
$dumpvars
b100 #
1"
b101 !
$end
#50
b101 #
0"
b100 !
#100
b10011 #
1"
b10100 !
#150
b10000110 #
0"
b10000101 !
#200
b10000000 #
1"
b10000001 !
#250
b10010110 #
0"
b10010101 !
#300
b10001111 #
1"
b10010000 !
#350
b10010110 #
0"
b10010101 !
#400
b10010000 #
1"
b10010001 !
#450
b10010101 #
0"
b10010100 !
