8_bit_ALU/Multi8.v
// Name: Yaohong Sabotinova
// 8-bit adder and sustractor 

module Multi8(z,a,b); 
output [15:0]z;
input [7:0]a,b; 

reg [15:0]z;
reg [15:0]y;
integer i; 

always @(a , b)
begin 
  y=a;
  z=0; // needs to zeroed
  for(i=0;i<8;i=i+1)
  begin
    if(b[i])
      z=z+y; // must be a blocking assignment
    y=y<<1;
  end
end
endmodule

8_bit_ALU/Multi8_tb.v
module Multi8_tb;

reg [7:0] a,b;

wire [15:0] z;



   initial
   
     begin
		$display("Simulation running..."); // Display info on monitor
        $dumpfile("Multi8_tb.vcd"); // Simulation results -> GTKWave
        $dumpvars(0,m01);  // Variables that will be in vcd file

        $monitor("%b + %b = %b", a,b,z);
		#0 	a = 8'b00000101; b = 8'b00001010;
		#50 a = 8'b00000100; b = 8'b00000000;
		#50 a = 8'b00010100; b = 8'b00010000;
		#50 a = 8'b10000101; b = 8'b00010010;
		#50 a = 8'b10000001; b = 8'b00011010;
		#50 a = 8'b10010101; b = 8'b00010010;
		#50 a = 8'b10010000; b = 8'b00011010;
		#50 a = 8'b10010101; b = 8'b00010000;
        #50 a = 8'b10010001; b = 8'b00010001;
		#50 a = 8'b10010100; b = 8'b00010010;
		#50 $finish;
     end


Multi8 m01(z,a,b);

endmodule

8_bit_ALU/Multi_tb.vcd
$date
	Thu May 14 23:12:28 2020
$end
$version
	Icarus Verilog
$end
$timescale
	1s
$end
$scope module Multi8_tb $end
$scope module m01 $end
$var wire 8 ! a [7:0] $end
$var wire 8 " b [7:0] $end
$var reg 16 # y [15:0] $end
$var reg 16 $ z [15:0] $end
$var integer 32 % i [31:0] $end
$upscope $end
$upscope $end
$enddefinitions $end
#0
$dumpvars
b1000 %
b110010 $
b10100000000 #
b1010 "
b101 !
$end
#50
b1000 %
b0 $
b10000000000 #
b0 "
b100 !
#100
b101000000 $
b1000 %
b1010000000000 #
b10000 "
b10100 !
#150
b1000 %
b100101011010 $
b1000010100000000 #
b10010 "
b10000101 !
#200
b1000 %
b110100011010 $
b1000000100000000 #
b11010 "
b10000001 !
#250
b1000 %
b101001111010 $
b1001010100000000 #
b10010 "
b10010101 !
#300
b1000 %
b111010100000 $
b1001000000000000 #
b11010 "
b10010000 !
#350
b1000 %
b100101010000 $
b1001010100000000 #
b10000 "
b10010101 !
#400
b1000 %
b100110100001 $
b1001000100000000 #
b10001 "
b10010001 !
#450
b1000 %
b101001101000 $
b1001010000000000 #
b10010 "
b10010100 !
