8_bit_ALU/PowerALU_Yaohong_Sabotinova.v
// Name: Yaohong Sabotinova
// 8-bit ALU

module ALU8(Cout,out,A,B,sel);
input [7:0] A,B;
input [3:0] sel;
output [7:0] out;
output Cout;

reg [7:0] result;
wire [8:0] w;

assign out = result;
assign w = {1'b0,A} + {1'b0,B};
assign Cout = w[8];
always@(*)
begin
    case(sel)
    4'b0000:
        result = A+B; //addtion
    4'b0001:
        result = A-B; //subtraction
    4'b0010:
        result = A*B; //multiplication
    4'b0011:
        result = (A<B)?8'd1:8'd0; //less than comparision
    4'b0100:
        result = A; //transfer A
    4'b0101:
        result = A+1; //increment A
    4'b0110:
        result = A-1; // decrement A
    4'b0111:
        result = ~A; // 1'complement of A
    4'b1000:
        result = A&B; //logical and
    4'b1001:
        result = A|B; //logical or
    4'b1010:
        result = A^B; //logical xor
    4'b1011:
        result = ~(A^B); // logical nor
    4'b1100:
        result = ~(A&B); // logical nand
    4'b1101:
        result = ~(A^B); // logical xnor
    4'b1110:
        result = (A>B)?8'd1:8'd0; //greater comparision
    4'b1111:
        result = (A==B)?8'd1:8'd0; // euqal comparison
    default: result = A+B;
    endcase

end

endmodule

8_bit_ALU/PowerALU_Yaohong_Sabotinova_tb.v
module ALU8_tb;

reg [7:0] A,B;
reg [3:0] sel;

wire [7:0] out;
wire Cout;

 ALU8 test_unit(
            .A(A),
			.B(B),  // ALU 8-bit Inputs                 
            .sel(sel),// ALU Selection
            .out(out), // ALU 8-bit Output
            .Cout(Cout) // Carry Out Flag
     );
    initial 
	
		begin

		$dumpfile("PowerALU_Yaohong_Sabotinova_tb.vcd"); // Simulation results -> GTKWave
        $dumpvars(0,alu01);  // Variables that will be in vcd file
       
		// // sel = 4'b0000;
		//  A = 8'b00000001;
		//  B = 8'b00000010;
 		$monitor("%b + %b + %b = %b %b", A, B, sel, Cout,out);
		#0 A = 8'b00100000; B = 8'b00010010; sel = 4'b0000;
		#50 A = 8'b00011000; B = 8'b00000100; sel = 4'b0001;
		#50 A = 8'b00000010; B = 8'b00100100; sel = 4'b0010;
		#50 A = 8'b00000100; B = 8'b10000000; sel = 4'b0011;
		#50 A = 8'b00000011; B = 8'b00001000; sel = 4'b0100;
		#50 A = 8'b00010100; B = 8'b00101000; sel = 4'b0101;
		#50 A = 8'b00000100; B = 8'b00100000; sel = 4'b0110;		
		#50 A = 8'b00100000; B = 8'b00011000; sel = 4'b0111;
		#50 A = 8'b01000001; B = 8'b00011001; sel = 4'b1000;
		#50 A = 8'b01000100; B = 8'b00001100; sel = 4'b1001;
		#50 A = 8'b00000110; B = 8'b00010000; sel = 4'b1011;
		#50 A = 8'b00010000; B = 8'b00000001; sel = 4'b1100;
		#50 A = 8'b00000010; B = 8'b00000011; sel = 4'b1101;
		#50 A = 8'b00010100; B = 8'b00000010; sel = 4'b1110;
		#50 A = 8'b00110000; B = 8'b00000100; sel = 4'b1111;
		#50;
 
    end
ALU8 alu01(Cout,out,A,B,sel);

endmodule

8_bit_ALU/PowerALU_Yaohong_Sabotinova_tb.vcd
$date
	Fri May 15 20:25:20 2020
$end
$version
	Icarus Verilog
$end
$timescale
	1s
$end
$scope module ALU8_tb $end
$scope module alu01 $end
$var wire 8 ! A [7:0] $end
$var wire 8 " B [7:0] $end
$var wire 1 # Cout $end
$var wire 8 $ out [7:0] $end
$var wire 4 % sel [3:0] $end
$var wire 9 & w [8:0] $end
$var reg 8 ' result [7:0] $end
$upscope $end
$upscope $end
$enddefinitions $end
#0
$dumpvars
b110010 '
b110010 &
b0 %
b110010 $
0#
b10010 "
b100000 !
$end
#50
b10100 $
b10100 '
b1 %
b100 "
b11100 &
b11000 !
#100
b1001000 '
b1001000 $
b10 %
b100100 "
b100110 &
b10 !
#150
b1 $
b1 '
b11 %
b10000000 "
b10000100 &
b100 !
#200
b11 '
b11 $
b100 %
b1000 "
b1011 &
b11 !
#250
b10101 $
b10101 '
b101 %
b101000 "
b111100 &
b10100 !
#300
b11 '
b11 $
b110 %
b100000 "
b100100 &
b100 !
#350
b11011111 $
b11011111 '
b111 %
b11000 "
b111000 &
b100000 !
#400
b1 '
b1 $
b1000 %
b11001 "
b1011010 &
b1000001 !
#450
b1001100 $
b1001100 '
b1001 %
b1100 "
b1010000 &
b1000100 !
#500
b11101001 '
b11101001 $
b1011 %
b10000 "
b10110 &
b110 !
#550
b11111111 $
b11111111 '
b1100 %
b1 "
b10001 &
b10000 !
#600
b11111110 '
b11111110 $
b1101 %
b11 "
b101 &
b10 !
#650
b1 $
b1 '
b1110 %
b10 "
b10110 &
b10100 !
#700
b0 '
b0 $
b1111 %
b100 "
b110100 &
b110000 !
