8_bit_ALU/Transfer.v
// Name: Yaohong Sabotinova 

module Transfer(a,b); 
output [7:0]b;
input [7:0]a; 

// reg [15:0]z;
reg [7:0] y;
reg [7:0] b;
integer i; 

always @(*)
begin 
  y=a;
  b=0;
  for(i=0;i<8;i=i+1)
  begin
      b[i]= y[i]; 
  end
end
endmodule

8_bit_ALU/Transfer_tb.v
module Transfer_tb;

reg [7:0] a;

wire [7:0] b;


   initial
   
     begin
		$display("Simulation running..."); // Display info on monitor
        $dumpfile("Transfer_tb.vcd"); // Simulation results -> GTKWave
        $dumpvars(0,t01);  // Variables that will be in vcd file

        $monitor("%b = %b", a, b);
		#0 	a = 8'b00000101;
		#50 a = 8'b00000100;
		#50 a = 8'b00010100;
		#50 a = 8'b10000101;
		#50 a = 8'b10000001;
		#50 a = 8'b10010101;
		#50 a = 8'b10010000;
		#50 a = 8'b10010101;
        #50 a = 8'b10010001;
		#50 a = 8'b10010100;
		#50 $finish;
     end


Transfer t01(a,b);

endmodule

8_bit_ALU/Transfer_tb.vcd
$date
	Fri May 15 19:53:15 2020
$end
$version
	Icarus Verilog
$end
$timescale
	1s
$end
$scope module Transfer_tb $end
$scope module t01 $end
$var wire 8 ! a [7:0] $end
$var reg 8 " b [7:0] $end
$var reg 8 # y [7:0] $end
$var integer 32 $ i [31:0] $end
$upscope $end
$upscope $end
$enddefinitions $end
#0
$dumpvars
b1000 $
b101 #
b101 "
b101 !
$end
#50
b1000 $
b100 "
b100 #
b100 !
#100
b1000 $
b10100 "
b10100 #
b10100 !
#150
b1000 $
b10000101 "
b10000101 #
b10000101 !
#200
b1000 $
b10000001 "
b10000001 #
b10000001 !
#250
b1000 $
b10010101 "
b10010101 #
b10010101 !
#300
b1000 $
b10010000 "
b10010000 #
b10010000 !
#350
b1000 $
b10010101 "
b10010101 #
b10010101 !
#400
b1000 $
b10010001 "
b10010001 #
b10010001 !
#450
b1000 $
b10010100 "
b10010100 #
b10010100 !
